{
  "profile_level": {
    "budget": {
      "f1_hybrid": {
        "mean": 0.881,
        "std": 0.1
      },
      "f1_rl": {
        "mean": 0.648,
        "std": 0.139
      },
      "f1_topsis": {
        "mean": 0.324,
        "std": 0.205
      },
      "ndcg_hybrid": {
        "mean": 0.912,
        "std": 0.079
      },
      "ndcg_rl": {
        "mean": 0.701,
        "std": 0.126
      },
      "ndcg_topsis": {
        "mean": 0.319,
        "std": 0.221
      }
    },
    "quality_seeker": {
      "f1_hybrid": {
        "mean": 0.914,
        "std": 0.08
      },
      "f1_rl": {
        "mean": 0.552,
        "std": 0.149
      },
      "f1_topsis": {
        "mean": 0.233,
        "std": 0.143
      },
      "ndcg_hybrid": {
        "mean": 0.944,
        "std": 0.053
      },
      "ndcg_rl": {
        "mean": 0.642,
        "std": 0.128
      },
      "ndcg_topsis": {
        "mean": 0.244,
        "std": 0.163
      }
    },
    "explorer": {
      "f1_hybrid": {
        "mean": 0.962,
        "std": 0.064
      },
      "f1_rl": {
        "mean": 0.605,
        "std": 0.117
      },
      "f1_topsis": {
        "mean": 0.448,
        "std": 0.144
      },
      "ndcg_hybrid": {
        "mean": 0.974,
        "std": 0.044
      },
      "ndcg_rl": {
        "mean": 0.672,
        "std": 0.109
      },
      "ndcg_topsis": {
        "mean": 0.528,
        "std": 0.158
      }
    },
    "loyal": {
      "f1_hybrid": {
        "mean": 0.933,
        "std": 0.09
      },
      "f1_rl": {
        "mean": 0.562,
        "std": 0.112
      },
      "f1_topsis": {
        "mean": 0.348,
        "std": 0.149
      },
      "ndcg_hybrid": {
        "mean": 0.954,
        "std": 0.061
      },
      "ndcg_rl": {
        "mean": 0.627,
        "std": 0.099
      },
      "ndcg_topsis": {
        "mean": 0.379,
        "std": 0.174
      }
    },
    "balanced": {
      "f1_hybrid": {
        "mean": 0.948,
        "std": 0.07
      },
      "f1_rl": {
        "mean": 0.71,
        "std": 0.133
      },
      "f1_topsis": {
        "mean": 0.648,
        "std": 0.123
      },
      "ndcg_hybrid": {
        "mean": 0.963,
        "std": 0.049
      },
      "ndcg_rl": {
        "mean": 0.767,
        "std": 0.111
      },
      "ndcg_topsis": {
        "mean": 0.715,
        "std": 0.12
      }
    }
  },
  "ndcg": {
    "hybrid": {
      "mean": 0.95,
      "std": 0.025,
      "ci_lo": 0.941,
      "ci_hi": 0.958
    },
    "rl": {
      "mean": 0.682,
      "std": 0.055,
      "ci_lo": 0.662,
      "ci_hi": 0.701
    },
    "topsis": {
      "mean": 0.437,
      "std": 0.071,
      "ci_lo": 0.412,
      "ci_hi": 0.462
    },
    "pop": {
      "mean": 0.078,
      "std": 0.066,
      "ci_lo": 0.055,
      "ci_hi": 0.102
    },
    "random": {
      "mean": 0.017,
      "std": 0.025,
      "ci_lo": 0.008,
      "ci_hi": 0.026
    }
  },
  "reward_shaping": {
    "0.00": {
      "hybrid": 0.714,
      "rl_only": 0.19,
      "delta": 0.525
    },
    "0.10": {
      "hybrid": 0.859,
      "rl_only": 0.408,
      "delta": 0.451
    },
    "0.20": {
      "hybrid": 0.928,
      "rl_only": 0.615,
      "delta": 0.312
    }
  }
}